Metadata-Version: 2.4
Name: imodelsx
Version: 1.0.10
Summary: Library to explain a dataset in natural language.
Home-page: https://github.com/csinva/imodelsX
Author: Chandan Singh, John X. Morris, Armin Askari, Divyanshu Aggarwal, Aliyah Hsu, Yuntian Deng
Author-email: chansingh@microsoft.com
Classifier: Programming Language :: Python :: 3
Classifier: License :: OSI Approved :: MIT License
Classifier: Operating System :: OS Independent
Requires-Python: >=3.9
Requires-Dist: datasets
Requires-Dist: dict_hash
Requires-Dist: imodels
Requires-Dist: langchain
Requires-Dist: numpy
Requires-Dist: pandas
Requires-Dist: scikit-learn>=1.2.0
Requires-Dist: scipy
Requires-Dist: spacy
Requires-Dist: torch
Requires-Dist: tqdm
Requires-Dist: transformers[torch]>=4.23.1
Requires-Dist: pyyaml
Dynamic: author
Dynamic: author-email
Dynamic: classifier
Dynamic: description
Dynamic: description-content-type
Dynamic: home-page
Dynamic: requires-dist
Dynamic: requires-python
Dynamic: summary
